pusteblume/__init__.py
pusteblume/__main__.py
pusteblume/cli.py
pusteblume/config.py
pusteblume/errors.py
pusteblume/messages.py
pusteblume/tasks.py
pusteblume-1.2.dist-info/LICENSE
pusteblume-1.2.dist-info/METADATA
pusteblume-1.2.dist-info/WHEEL
pusteblume-1.2.dist-info/entry_points.txt
pusteblume-1.2.dist-info/top_level.txt
pusteblume-1.2.dist-info/RECORD
