Metadata-Version: 2.1
Name: pusteblume
Version: 1.2
Summary: Light-weight time tracking tool.
Home-page: https://github.com/PascalinDe/pusteblume
Author: Carine Dengler
Author-email: pusteblume@pascalin.de
Classifier: License :: OSI Approved :: GNU General Public License v3 (GPLv3)
Classifier: Operating System :: POSIX :: Linux
Classifier: Programming Language :: Python :: 3.11
License-File: LICENSE
